CHANGES.txt
LICENSE.txt
MANIFEST.in
README.txt
setup.py
js/__init__.py
js.suggest.egg-info/PKG-INFO
js.suggest.egg-info/SOURCES.txt
js.suggest.egg-info/dependency_links.txt
js.suggest.egg-info/entry_points.txt
js.suggest.egg-info/namespace_packages.txt
js.suggest.egg-info/not-zip-safe
js.suggest.egg-info/requires.txt
js.suggest.egg-info/top_level.txt
js/suggest/__init__.py
js/suggest/test_suggest.js.txt
js/suggest/resources/suggest.js
js/suggest/resources/suggest.min.js