Metadata-Version: 1.0
Name: js.suggest
Version: 2.3
Summary: Fanstatic packaging of suggest.js
Home-page: UNKNOWN
Author: UNKNOWN
Author-email: UNKNOWN
License: MIT
Platform: UNKNOWN
